taxtree.py
taxtree-1.0.4.dist-info/METADATA
taxtree-1.0.4.dist-info/WHEEL
taxtree-1.0.4.dist-info/entry_points.txt
taxtree-1.0.4.dist-info/top_level.txt
taxtree-1.0.4.dist-info/RECORD
