Metadata-Version: 2.1
Name: taxtree
Version: 1.0.4
Summary: Python library for NCBI taxonomy database.
Home-page: https://github.com/bushenjie/taxtree
Author: bushenjie
Author-email: bushenjie@gmail.com
License: MIT
Platform: UNKNOWN
Classifier: License :: OSI Approved :: MIT License
Classifier: Programming Language :: Python
Classifier: Programming Language :: Python :: 3
Classifier: Programming Language :: Python :: 3.6
Classifier: Programming Language :: Python :: Implementation :: CPython
Classifier: Programming Language :: Python :: Implementation :: PyPy
Requires-Python: >=3.6.0
Requires-Dist: click
Requires-Dist: requests
Requires-Dist: humanize
Requires-Dist: sqlalchemy
